Workbook
Name Slicer_Channel: #N/A
Name Slicer_Channel1: #N/A
Name Slicer_Country: #N/A
Name Slicer_Country1: #N/A
Name Slicer_Country3: #N/A
Name Slicer_Month: #N/A
Name Slicer_ProductCategory: #N/A
Name Slicer_ProductCategory1: #N/A
Name Slicer_Region: #N/A
Name Slicer_Region1: #N/A
Name Slicer_Salesperson: #N/A

Sheet Brief
A1: Assignment
A2: Excel Mastery Assignment: Sales Operations & Analytics
A4: Overview:
A5: You are an analyst for a multi-regional electronics distributor. The 'Data' sheet contains 632 rows and 15 columns of transactional data with intentional data-quality issues.
A6: Your job is to clean, enrich, analyze, and present insights via a dynamic dashboard.
A8: Part A — Data Cleaning & Preparation:
A9: 1) Create a staging table where you:
A10: • Remove exact duplicate rows (define and document your duplicate criteria).
A11: • Fix data types (dates as Dates, numeric fields as numbers).
A12: • Handle missing values for City, Salesperson, and Channel using reasonable business logic (document your approach).
A13: • Flag and correct suspicious UnitPrice values (e.g., negative prices) and discounts (e.g., > 30%).
A14: • Ensure RequiredDate is not earlier than OrderDate; where it is, impute a corrected RequiredDate (explain your rule).
... A67: 15) Ensure your dashboard responds to slicers without broken references.

Sheet DASHBOARD
P7: Global Discount cap : | Q7: 0.2
P8: Unit Cost Inflation Rate : | Q8: 0.15
P9: Quantity Uplift: | Q9: 0.2

Sheet staging data
A1: OrderID | B1: Order date in months | C1: Quarters | D1: Year | E1: Month | F1: OrderDate | G1: Corrected.Required date | H1: RequiredDate | I1: %leadtime >7days | J1: Corrected Leadtime days | K1: Leadtime days | L1: Region | M1: Country | N1: City | O1: CustomerSegment | P1: Channel | Q1: Salesperson | R1: ProductCategory | S1: SKU | T1: UnitCost | U1: Price bands | V1: Corrected unit Price(Ksh) | W1: UnitPrice | X1: Discount.Pct | Y1: Quantity | Z1: Discount(KES) | AA1: Gross Revenue(KES) | AB1: NET Revenue(KES) | AC1: Cost of Goods(KES) | AD1: Gross Profit(KES) | AE1: Net Profit(KES) | AF1: Margin % | AG1: disc cap | AH1: Infl cap | AI1: uplift cost
A2: ORD -2025-739842 | B2: 44928 | C2: ="Q" & ROUNDUP(MONTH(B2)/3,0) -> Q1 | D2: =TEXT(F2,"YYYY") -> 2025 | E2: =TEXT(F2,"MMM") -> Feb | F2: 45716 | G2: =IF(H2>=F2, H2, (H2-K2)) -> 45726 | H2: 45726 | I2: =IF(J2>=7,"Achieved","Not achieved") -> Achieved | J2: =_xlfn.DAYS(G2,F2) -> 10 | K2: =_xlfn.DAYS(H2,F2) -> 10 | L2: Asia | M2: Japan | N2: Osaka | O2: Education | P2: Distributor | Q2: N. Brown | R2: Laptops | S2: LAP-3017 | T2: 51.86 | U2: =IF(V2<=QUARTILE(V2:V633,1),"Low",IF(V2>=QUARTILE(V2:V633,3),"High","Medium")) -> Low | V2: =ABS(W2) -> 45.98 | W2: 45.98 | X2: 0.173 | Y2: 7 | Z2: =X2*V2 -> 7.95454 | AA2: =(V2*Y2)*(1-X2) -> 266.17822 | AB2: =AA2-Z2 -> 258.22368 | AC2: =T2*Y2 -> 363.02 | AD2: =AA2-AC2 -> -96.84178 | AE2: =AB2-AC2 -> -104.79632 | AF2: =IF(AA2=0,0,AA2/AC2) -> 0.73323293 | AG2: =IF(DASHBOARD!$Q$7>'staging data'!X2,'staging data'!X2,DASHBOARD!$Q$7) -> 0.173 | AH2: =(100%+DASHBOARD!$Q$8)*'staging data'!T2 -> 59.639 | AI2: =(100%+DASHBOARD!$Q$9)*'staging data'!Y2 -> 8.4
A3: ORD-2025-728935 | B3: 44933 | C3: ="Q" & ROUNDUP(MONTH(B3)/3,0) -> Q1 | D3: =TEXT(F3,"YYYY") -> 2023 | E3: =TEXT(F3,"MMM") -> Nov | F3: 45249 | G3: =IF(H3>=F3, H3, (H3-K3)) -> 45279 | H3: 45279 | I3: =IF(J3>=7,"Achieved","Not achieved") -> Achieved | J3: =_xlfn.DAYS(G3,F3) -> 30 | K3: =_xlfn.DAYS(H3,F3) -> 30 | L3: Asia | M3: Japan | N3: Nagoya | O3: Consumer | P3: Retail | Q3: L. Okafor | R3: Phones | S3: PHN-9184 | T3: 807.11 | U3: =IF(V3<=QUARTILE(V3:V633,1),"Low",IF(V3>=QUARTILE(V3:V633,3),"High","Medium")) -> Medium | V3: =ABS(W3) -> 1853.86 | W3: 1853.86 | X3: 0.139 | Y3: 8 | Z3: =X3*V3 -> 257.68654 | AA3: =(V3*Y3)*(1-X3) -> 12769.388 | AB3: =AA3-Z3 -> 12511.701 | AC3: =T3*Y3 -> 6456.88 | AD3: =AA3-AC3 -> 6312.5077 | AE3: =AB3-AC3 -> 6054.8211 | AF3: =IF(AA3=0,0,AA3/AC3) -> 1.9776405 | AG3: =IF(DASHBOARD!$Q$7>'staging data'!X3,'staging data'!X3,DASHBOARD!$Q$7) -> 0.139 | AH3: =(100%+DASHBOARD!$Q$8)*'staging data'!T3 -> 928.1765 | AI3: =(100%+DASHBOARD!$Q$9)*'staging data'!Y3 -> 9.6
A4: ORD-2023-455933 | B4: 44936 | C4: ="Q" & ROUNDUP(MONTH(B4)/3,0) -> Q1 | D4: =TEXT(F4,"YYYY") -> 2023 | E4: =TEXT(F4,"MMM") -> Dec | F4: 45267 | G4: =IF(H4>=F4, H4, (H4-K4)) -> 45293 | H4: 45293 | I4: =IF(J4>=7,"Achieved","Not achieved") -> Achieved | J4: =_xlfn.DAYS(G4,F4) -> 26 | K4: =_xlfn.DAYS(H4,F4) -> 26 | L4: Europe | M4: Germany | N4: Frankfurt | O4: Enterprise | P4: Distributor | Q4: E. Garcia | R4: Components | S4: CMP-1940 | T4: 1071.99 | U4: =IF(V4<=QUARTILE(V4:V633,1),"Low",IF(V4>=QUARTILE(V4:V633,3),"High","Medium")) -> High | V4: =ABS(W4) -> 2397.3 | W4: 2397.3 | X4: 0.062 | Y4: 18 | Z4: =X4*V4 -> 148.6326 | AA4: =(V4*Y4)*(1-X4) -> 40476.013 | AB4: =AA4-Z4 -> 40327.381 | AC4: =T4*Y4 -> 19295.82 | AD4: =AA4-AC4 -> 21180.193 | AE4: =AB4-AC4 -> 21031.561 | AF4: =IF(AA4=0,0,AA4/AC4) -> 2.0976571 | AG4: =IF(DASHBOARD!$Q$7>'staging data'!X4,'staging data'!X4,DASHBOARD!$Q$7) -> 0.062 | AH4: =(100%+DASHBOARD!$Q$8)*'staging data'!T4 -> 1232.7885 | AI4: =(100%+DASHBOARD!$Q$9)*'staging data'!Y4 -> 21.6
A5: ORD-2023-961864 | B5: 44938 | C5: ="Q" & ROUNDUP(MONTH(B5)/3,0) -> Q1 | D5: =TEXT(F5,"YYYY") -> 2023 | E5: =TEXT(F5,"MMM") -> Jun | F5: 45100 | G5: =IF(H5>=F5, H5, (H5-K5)) -> 45125 | H5: 45125 | I5: =IF(J5>=7,"Achieved","Not achieved") -> Achieved | J5: =_xlfn.DAYS(G5,F5) -> 25 | K5: =_xlfn.DAYS(H5,F5) -> 25 | L5: Americas | M5: Canada | N5: Vancouver | O5: Enterprise | P5: Online | Q5: N. Brown | R5: Phones | S5: PHN-4677 | T5: 807.02 | U5: =IF(V5<=QUARTILE(V5:V634,1),"Low",IF(V5>=QUARTILE(V5:V634,3),"High","Medium")) -> Medium | V5: =ABS(W5) -> 1435.54 | W5: 1435.54 | X5: 0 | Y5: 23 | Z5: =X5*V5 -> 0 | AA5: =(V5*Y5)*(1-X5) -> 33017.42 | AB5: =AA5-Z5 -> 33017.42 | AC5: =T5*Y5 -> 18561.46 | AD5: =AA5-AC5 -> 14455.96 | AE5: =AB5-AC5 -> 14455.96 | AF5: =IF(AA5=0,0,AA5/AC5) -> 1.7788159 | AG5: =IF(DASHBOARD!$Q$7>'staging data'!X5,'staging data'!X5,DASHBOARD!$Q$7) -> 0 | AH5: =(100%+DASHBOARD!$Q$8)*'staging data'!T5 -> 928.073 | AI5: =(100%+DASHBOARD!$Q$9)*'staging data'!Y5 -> 27.6
A6: ORD-2023-921939 | B6: 44939 | C6: ="Q" & ROUNDUP(MONTH(B6)/3,0) -> Q1 | D6: =TEXT(F6,"YYYY") -> 2023 | E6: =TEXT(F6,"MMM") -> Aug | F6: 45141 | G6: =IF(H6>=F6, H6, (H6-K6)) -> 45168 | H6: 45168 | I6: =IF(J6>=7,"Achieved","Not achieved") -> Achieved | J6: =_xlfn.DAYS(G6,F6) -> 27 | K6: =_xlfn.DAYS(H6,F6) -> 27 | L6: Asia | M6: China | N6: Shanghai | O6: Consumer | P6: Distributor | Q6: N. Brown | R6: Monitors | S6: MON-3773 | T6: 226.04 | U6: =IF(V6<=QUARTILE(V6:V635,1),"Low",IF(V6>=QUARTILE(V6:V635,3),"High","Medium")) -> Low | V6: =ABS(W6) -> 545.72 | W6: 545.72 | X6: 0.151 | Y6: 11 | Z6: =X6*V6 -> 82.40372 | AA6: =(V6*Y6)*(1-X6) -> 5096.4791 | AB6: =AA6-Z6 -> 5014.0754 | AC6: =T6*Y6 -> 2486.44 | AD6: =AA6-AC6 -> 2610.0391 | AE6: =AB6-AC6 -> 2527.6354 | AF6: =IF(AA6=0,0,AA6/AC6) -> 2.0497093 | AG6: =IF(DASHBOARD!$Q$7>'staging data'!X6,'staging data'!X6,DASHBOARD!$Q$7) -> 0.151 | AH6: =(100%+DASHBOARD!$Q$8)*'staging data'!T6 -> 259.946 | AI6: =(100%+DASHBOARD!$Q$9)*'staging data'!Y6 -> 13.2
A7: ORD-2023-548934 | B7: 44941 | C7: ="Q" & ROUNDUP(MONTH(B7)/3,0) -> Q1 | D7: =TEXT(F7,"YYYY") -> 2023 | E7: =TEXT(F7,"MMM") -> Dec | F7: 45282 | G7: =IF(H7>=F7, H7, (H7-K7)) -> 45307 | H7: 45307 | I7: =IF(J7>=7,"Achieved","Not achieved") -> Achieved | J7: =_xlfn.DAYS(G7,F7) -> 25 | K7: =_xlfn.DAYS(H7,F7) -> 25 | L7: Asia | M7: India | N7: Hyderabad | O7: Small Business | P7: Retail | Q7: A. Patel | R7: Components | S7: CMP-1555 | T7: 1346.81 | U7: =IF(V7<=QUARTILE(V7:V636,1),"Low",IF(V7>=QUARTILE(V7:V636,3),"High","Medium")) -> Medium | V7: =ABS(W7) -> 978.09 | W7: 978.09 | X7: 0.159 | Y7: 17 | Z7: =X7*V7 -> 155.51631 | AA7: =(V7*Y7)*(1-X7) -> 13983.753 | AB7: =AA7-Z7 -> 13828.236 | AC7: =T7*Y7 -> 22895.77 | AD7: =AA7-AC7 -> -8912.0173 | AE7: =AB7-AC7 -> -9067.5336 | AF7: =IF(AA7=0,0,AA7/AC7) -> 0.61075704 | AG7: =IF(DASHBOARD!$Q$7>'staging data'!X7,'staging data'!X7,DASHBOARD!$Q$7) -> 0.159 | AH7: =(100%+DASHBOARD!$Q$8)*'staging data'!T7 -> 1548.8315 | AI7: =(100%+DASHBOARD!$Q$9)*'staging data'!Y7 -> 20.4
A8: ORD-2023-249805 | B8: 44945 | C8: ="Q" & ROUNDUP(MONTH(B8)/3,0) -> Q1 | D8: =TEXT(F8,"YYYY") -> 2023 | E8: =TEXT(F8,"MMM") -> Nov | F8: 45249 | G8: =IF(H8>=F8, H8, (H8-K8)) -> 45272 | H8: 45272 | I8: =IF(J8>=7,"Achieved","Not achieved") -> Achieved | J8: =_xlfn.DAYS(G8,F8) -> 23 | K8: =_xlfn.DAYS(H8,F8) -> 23 | L8: Asia | M8: India | N8: Delhi | O8: Small Business | P8: Direct | Q8: C. Otieno | R8: Networking | S8: NET-2460 | T8: 1349.04 | U8: =IF(V8<=QUARTILE(V8:V637,1),"Low",IF(V8>=QUARTILE(V8:V637,3),"High","Medium")) -> High | V8: =ABS(W8) -> 2636.6 | W8: 2636.6 | X8: 0.114 | Y8: 14 | Z8: =X8*V8 -> 300.5724 | AA8: =(V8*Y8)*(1-X8) -> 32704.386 | AB8: =AA8-Z8 -> 32403.814 | AC8: =T8*Y8 -> 18886.56 | AD8: =AA8-AC8 -> 13817.826 | AE8: =AB8-AC8 -> 13517.254 | AF8: =IF(AA8=0,0,AA8/AC8) -> 1.7316222 | AG8: =IF(DASHBOARD!$Q$7>'staging data'!X8,'staging data'!X8,DASHBOARD!$Q$7) -> 0.114 | AH8: =(100%+DASHBOARD!$Q$8)*'staging data'!T8 -> 1551.396 | AI8: =(100%+DASHBOARD!$Q$9)*'staging data'!Y8 -> 16.8
A9: ORD-2023-561823 | B9: 44946 | C9: ="Q" & ROUNDUP(MONTH(B9)/3,0) -> Q1 | D9: =TEXT(F9,"YYYY") -> 2023 | E9: =TEXT(F9,"MMM") -> Aug | F9: 45141 | G9: =IF(H9>=F9, H9, (H9-K9)) -> 45141 | H9: 45140 | I9: =IF(J9>=7,"Achieved","Not achieved") -> Not achieved | J9: =_xlfn.DAYS(G9,F9) -> 0 | K9: =_xlfn.DAYS(H9,F9) -> -1 | L9: Asia | M9: China | N9: Shanghai | O9: Non-Profit | P9: Direct | Q9: J. Njeri | R9: Networking | S9: NET-4735 | T9: 1021.97 | U9: =IF(V9<=QUARTILE(V9:V638,1),"Low",IF(V9>=QUARTILE(V9:V638,3),"High","Medium")) -> High | V9: =ABS(W9) -> 2296.25 | W9: 2296.25 | X9: 0.161 | Y9: 26 | Z9: =X9*V9 -> 369.69625 | AA9: =(V9*Y9)*(1-X9) -> 50090.397 | AB9: =AA9-Z9 -> 49720.701 | AC9: =T9*Y9 -> 26571.22 | AD9: =AA9-AC9 -> 23519.177 | AE9: =AB9-AC9 -> 23149.481 | AF9: =IF(AA9=0,0,AA9/AC9) -> 1.8851373 | AG9: =IF(DASHBOARD!$Q$7>'staging data'!X9,'staging data'!X9,DASHBOARD!$Q$7) -> 0.161 | AH9: =(100%+DASHBOARD!$Q$8)*'staging data'!T9 -> 1175.2655 | AI9: =(100%+DASHBOARD!$Q$9)*'staging data'!Y9 -> 31.2
A10: ORD-2025-649633 | B10: 44948 | C10: ="Q" & ROUNDUP(MONTH(B10)/3,0) -> Q1 | D10: =TEXT(F10,"YYYY") -> 2024 | E10: =TEXT(F10,"MMM") -> Jul | F10: 45501 | G10: =IF(H10>=F10, H10, (H10-K10)) -> 45527 | H10: 45527 | I10: =IF(J10>=7,"Achieved","Not achieved") -> Achieved | J10: =_xlfn.DAYS(G10,F10) -> 26 | K10: =_xlfn.DAYS(H10,F10) -> 26 | L10: Asia | M10: India | N10: Hyderabad | O10: Corporate | P10: Retail | Q10: J. Njeri | R10: Networking | S10: NET-4675 | T10: 1339.24 | U10: =IF(V10<=QUARTILE(V10:V639,1),"Low",IF(V10>=QUARTILE(V10:V639,3),"High","Medium")) -> Medium | V10: =ABS(W10) -> 1558.89 | W10: 1558.89 | X10: 0.192 | Y10: 24 | Z10: =X10*V10 -> 299.30688 | AA10: =(V10*Y10)*(1-X10) -> 30229.995 | AB10: =AA10-Z10 -> 29930.688 | AC10: =T10*Y10 -> 32141.76 | AD10: =AA10-AC10 -> -1911.7651 | AE10: =AB10-AC10 -> -2211.072 | AF10: =IF(AA10=0,0,AA10/AC10) -> 0.94052083 | AG10: =IF(DASHBOARD!$Q$7>'staging data'!X10,'staging data'!X10,DASHBOARD!$Q$7) -> 0.192 | AH10: =(100%+DASHBOARD!$Q$8)*'staging data'!T10 -> 1540.126 | AI10: =(100%+DASHBOARD!$Q$9)*'staging data'!Y10 -> 28.8
A11: ORD-2023-885216 | B11: 44948 | C11: ="Q" & ROUNDUP(MONTH(B11)/3,0) -> Q1 | D11: =TEXT(F11,"YYYY") -> 2025 | E11: =TEXT(F11,"MMM") -> Jul | F11: 45857 | G11: =IF(H11>=F11, H11, (H11-K11)) -> 45869 | H11: 45869 | I11: =IF(J11>=7,"Achieved","Not achieved") -> Achieved | J11: =_xlfn.DAYS(G11,F11) -> 12 | K11: =_xlfn.DAYS(H11,F11) -> 12 | L11: Africa | M11: Kenya | N11: Nairobi | O11: Small Business | P11: Marketplace | Q11: O. Wang | R11: Accessories | S11: ACC-1028 | T11: 619.64 | U11: =IF(V11<=QUARTILE(V11:V640,1),"Low",IF(V11>=QUARTILE(V11:V640,3),"High","Medium")) -> Medium | V11: =ABS(W11) -> 861.16 | W11: 861.16 | X11: 0.113 | Y11: 14 | Z11: =X11*V11 -> 97.31108 | AA11: =(V11*Y11)*(1-X11) -> 10693.885 | AB11: =AA11-Z11 -> 10596.574 | AC11: =T11*Y11 -> 8674.96 | AD11: =AA11-AC11 -> 2018.9249 | AE11: =AB11-AC11 -> 1921.6138 | AF11: =IF(AA11=0,0,AA11/AC11) -> 1.2327302 | AG11: =IF(DASHBOARD!$Q$7>'staging data'!X11,'staging data'!X11,DASHBOARD!$Q$7) -> 0.113 | AH11: =(100%+DASHBOARD!$Q$8)*'staging data'!T11 -> 712.586 | AI11: =(100%+DASHBOARD!$Q$9)*'staging data'!Y11 -> 16.8
A12: ORD-2024-817997 | B12: 44952 | C12: ="Q" & ROUNDUP(MONTH(B12)/3,0) -> Q1 | D12: =TEXT(F12,"YYYY") -> 2025 | E12: =TEXT(F12,"MMM") -> Apr | F12: 45764 | G12: =IF(H12>=F12, H12, (H12-K12)) -> 45780 | H12: 45780 | I12: =IF(J12>=7,"Achieved","Not achieved") -> Achieved | J12: =_xlfn.DAYS(G12,F12) -> 16 | K12: =_xlfn.DAYS(H12,F12) -> 16 | L12: Americas | M12: Brazil | N12: Rio de Janeiro | O12: Consumer | P12: Marketplace | Q12: J. Njeri | R12: Networking | S12: NET-8610 | T12: 168.68 | U12: =IF(V12<=QUARTILE(V12:V641,1),"Low",IF(V12>=QUARTILE(V12:V641,3),"High","Medium")) -> Low | V12: =ABS(W12) -> 413.34 | W12: 413.34 | X12: 0.186 | Y12: 7 | Z12: =X12*V12 -> 76.88124 | AA12: =(V12*Y12)*(1-X12) -> 2355.2113 | AB12: =AA12-Z12 -> 2278.3301 | AC12: =T12*Y12 -> 1180.76 | AD12: =AA12-AC12 -> 1174.4513 | AE12: =AB12-AC12 -> 1097.5701 | AF12: =IF(AA12=0,0,AA12/AC12) -> 1.9946571 | AG12: =IF(DASHBOARD!$Q$7>'staging data'!X12,'staging data'!X12,DASHBOARD!$Q$7) -> 0.186 | AH12: =(100%+DASHBOARD!$Q$8)*'staging data'!T12 -> 193.982 | AI12: =(100%+DASHBOARD!$Q$9)*'staging data'!Y12 -> 8.4
A13: ORD-2025-907040 | B13: 44953 | C13: ="Q" & ROUNDUP(MONTH(B13)/3,0) -> Q1 | D13: =TEXT(F13,"YYYY") -> 2023 | E13: =TEXT(F13,"MMM") -> Sept | F13: 45177 | G13: =IF(H13>=F13, H13, (H13-K13)) -> 45183 | H13: 45183 | I13: =IF(J13>=7,"Achieved","Not achieved") -> Not achieved | J13: =_xlfn.DAYS(G13,F13) -> 6 | K13: =_xlfn.DAYS(H13,F13) -> 6 | L13: Africa | M13: Kenya | N13: Nakuru | O13: Education | P13: Direct | Q13: I. Johnson | R13: Accessories | S13: ACC-4766 | T13: 251.03 | U13: =IF(V13<=QUARTILE(V13:V642,1),"Low",IF(V13>=QUARTILE(V13:V642,3),"High","Medium")) -> Low | V13: =ABS(W13) -> 411.48 | W13: 411.48 | X13: 0.165 | Y13: 3 | Z13: =X13*V13 -> 67.8942 | AA13: =(V13*Y13)*(1-X13) -> 1030.7574 | AB13: =AA13-Z13 -> 962.8632 | AC13: =T13*Y13 -> 753.09 | AD13: =AA13-AC13 -> 277.6674 | AE13: =AB13-AC13 -> 209.7732 | AF13: =IF(AA13=0,0,AA13/AC13) -> 1.3687041 | AG13: =IF(DASHBOARD!$Q$7>'staging data'!X13,'staging data'!X13,DASHBOARD!$Q$7) -> 0.165 | AH13: =(100%+DASHBOARD!$Q$8)*'staging data'!T13 -> 288.6845 | AI13: =(100%+DASHBOARD!$Q$9)*'staging data'!Y13 -> 3.6
A14: ORD-2024-756884 | B14: 44955 | C14: ="Q" & ROUNDUP(MONTH(B14)/3,0) -> Q1 | D14: =TEXT(F14,"YYYY") -> 2025 | E14: =TEXT(F14,"MMM") -> Jul | F14: 45849 | G14: =IF(H14>=F14, H14, (H14-K14)) -> 45854 | H14: 45854 | I14: =IF(J14>=7,"Achieved","Not achieved") -> Not achieved | J14: =_xlfn.DAYS(G14,F14) -> 5 | K14: =_xlfn.DAYS(H14,F14) -> 5 | L14: Europe | M14: United Kingdom | N14: London | O14: Enterprise | P14: Online | Q14: K. Singh | R14: Printers | S14: PRN-5753 | T14: 930.03 | U14: =IF(V14<=QUARTILE(V14:V643,1),"Low",IF(V14>=QUARTILE(V14:V643,3),"High","Medium")) -> Medium | V14: =ABS(W14) -> 1086.68 | W14: 1086.68 | X14: 0.109 | Y14: 26 | Z14: =X14*V14 -> 118.44812 | AA14: =(V14*Y14)*(1-X14) -> 25174.029 | AB14: =AA14-Z14 -> 25055.581 | AC14: =T14*Y14 -> 24180.78 | AD14: =AA14-AC14 -> 993.24888 | AE14: =AB14-AC14 -> 874.80076 | AF14: =IF(AA14=0,0,AA14/AC14) -> 1.041076 | AG14: =IF(DASHBOARD!$Q$7>'staging data'!X14,'staging data'!X14,DASHBOARD!$Q$7) -> 0.109 | AH14: =(100%+DASHBOARD!$Q$8)*'staging data'!T14 -> 1069.5345 | AI14: =(100%+DASHBOARD!$Q$9)*'staging data'!Y14 -> 31.2
A15: ORD-2023-755337 | B15: 44955 | C15: ="Q" & ROUNDUP(MONTH(B15)/3,0) -> Q1 | D15: =TEXT(F15,"YYYY") -> 2024 | E15: =TEXT(F15,"MMM") -> Oct | F15: 45578 | G15: =IF(H15>=F15, H15, (H15-K15)) -> 45589 | H15: 45589 | I15: =IF(J15>=7,"Achieved","Not achieved") -> Achieved | J15: =_xlfn.DAYS(G15,F15) -> 11 | K15: =_xlfn.DAYS(H15,F15) -> 11 | L15: Europe | M15: France | N15: Paris | O15: Education | P15: Distributor | Q15: F. Müller | R15: Components | S15: CMP-5006 | T15: 816.7 | U15: =IF(V15<=QUARTILE(V15:V644,1),"Low",IF(V15>=QUARTILE(V15:V644,3),"High","Medium")) -> Medium | V15: =ABS(W15) -> 1010.75 | W15: 1010.75 | X15: 0.047 | Y15: 43 | Z15: =X15*V15 -> 47.50525 | AA15: =(V15*Y15)*(1-X15) -> 41419.524 | AB15: =AA15-Z15 -> 41372.019 | AC15: =T15*Y15 -> 35118.1 | AD15: =AA15-AC15 -> 6301.4242 | AE15: =AB15-AC15 -> 6253.919 | AF15: =IF(AA15=0,0,AA15/AC15) -> 1.1794352 | AG15: =IF(DASHBOARD!$Q$7>'staging data'!X15,'staging data'!X15,DASHBOARD!$Q$7) -> 0.047 | AH15: =(100%+DASHBOARD!$Q$8)*'staging data'!T15 -> 939.205 | AI15: =(100%+DASHBOARD!$Q$9)*'staging data'!Y15 -> 51.6
... A631: ORD-2025-168148 | B631: 45914 | C631: ="Q" & ROUNDUP(MONTH(B631)/3,0) -> Q3 | D631: =TEXT(F631,"YYYY") -> 2025 | E631: =TEXT(F631,"MMM") -> Mar | F631: 45745 | G631: =IF(H631>=F631, H631, (H631-K631)) -> 45749 | H631: 45749 | I631: =IF(J631>=7,"Achieved","Not achieved") -> Not achieved | J631: =_xlfn.DAYS(G631,F631) -> 4 | K631: =_xlfn.DAYS(H631,F631) -> 4 | L631: Africa | M631: Nigeria | N631: Lagos | O631: Non-Profit | P631: Marketplace | Q631: G. Dubois | R631: Phones | S631: PHN-4556 | T631: 259.93 | U631: =IF(V631<=QUARTILE(V631:V1260,1),"Low",IF(V631>=QUARTILE(V631:V1260,3),"High","Medium")) -> Low | V631: =ABS(W631) -> 255.94 | W631: 255.94 | X631: 0.072 | Y631: 22 | Z631: =X631*V631 -> 18.42768 | AA631: =(V631*Y631)*(1-X631) -> 5225.271 | AB631: =AA631-Z631 -> 5206.8434 | AC631: =T631*Y631 -> 5718.46 | AD631: =AA631-AC631 -> -493.18896 | AE631: =AB631-AC631 -> -511.61664 | AF631: =IF(AA631=0,0,AA631/AC631) -> 0.91375493 | AG631: =IF(DASHBOARD!$Q$7>'staging data'!X631,'staging data'!X631,DASHBOARD!$Q$7) -> 0.072 | AH631: =(100%+DASHBOARD!$Q$8)*'staging data'!T631 -> 298.9195 | AI631: =(100%+DASHBOARD!$Q$9)*'staging data'!Y631 -> 26.4
A632: ORD-2024-275203 | B632: 45915 | C632: ="Q" & ROUNDUP(MONTH(B632)/3,0) -> Q3 | D632: =TEXT(F632,"YYYY") -> 2024 | E632: =TEXT(F632,"MMM") -> Mar | F632: 45362 | G632: =IF(H632>=F632, H632, (F632+K632)) -> 45388 | H632: 45388 | I632: =IF(J632>=7,"Achieved","Not achieved") -> Achieved | J632: =_xlfn.DAYS(G632,F632) -> 26 | K632: =_xlfn.DAYS(H632,F632) -> 26 | L632: Africa | M632: Kenya | N632: Kisumu | O632: Corporate | P632: Retail | Q632: C. Otieno | R632: Components | S632: CMP-8270 | T632: 279.24 | U632: =IF(V632<=QUARTILE(V632:V1261,1),"Low",IF(V632>=QUARTILE(V632:V1261,3),"High","Medium")) -> Low | V632: =ABS(W632) -> 608.9 | W632: 608.9 | X632: 0.112 | Y632: 9 | Z632: =X632*V632 -> 68.1968 | AA632: =(V632*Y632)*(1-X632) -> 4866.3288 | AB632: =AA632-Z632 -> 4798.132 | AC632: =T632*Y632 -> 2513.16 | AD632: =AA632-AC632 -> 2353.1688 | AE632: =AB632-AC632 -> 2284.972 | AF632: =IF(AA632=0,0,AA632/AD632) -> 2.0679897 | AG632: =IF(DASHBOARD!$Q$7>'staging data'!X632,'staging data'!X632,DASHBOARD!$Q$7) -> 0.112 | AH632: =(100%+DASHBOARD!$Q$8)*'staging data'!T632 -> 321.126 | AI632: =(100%+DASHBOARD!$Q$9)*'staging data'!Y632 -> 10.8
A633: ORD-2024-358795 | B633: 45915 | C633: ="Q" & ROUNDUP(MONTH(B633)/3,0) -> Q3 | D633: =TEXT(F633,"YYYY") -> 2024 | E633: =TEXT(F633,"MMM") -> Oct | F633: 45588 | G633: =IF(H633>=F633, H633, (H633-K633)) -> 45588 | H633: 45587 | I633: =IF(J633>=7,"Achieved","Not achieved") -> Not achieved | J633: =_xlfn.DAYS(G633,F633) -> 0 | K633: =_xlfn.DAYS(H633,F633) -> -1 | L633: Africa | M633: Nigeria | N633: Port Harcourt | O633: Education | P633: Online | Q633: J. Njeri | R633: Printers | S633: PRN-9322 | T633: 1084.39 | U633: =IF(V633<=QUARTILE(V633:V1262,1),"Low",IF(V633>=QUARTILE(V633:V1262,3),"High","Medium")) -> Low | V633: =ABS(W633) -> 759.33 | W633: 759.33 | X633: 0.237 | Y633: 31 | Z633: =X633*V633 -> 179.96121 | AA633: =(V633*Y633)*(1-X633) -> 17960.432 | AB633: =AA633-Z633 -> 17780.471 | AC633: =T633*Y633 -> 33616.09 | AD633: =AA633-AC633 -> -15655.658 | AE633: =AB633-AC633 -> -15835.619 | AF633: =IF(AA633=0,0,AA633/AC633) -> 0.53428083 | AG633: =IF(DASHBOARD!$Q$7>'staging data'!X633,'staging data'!X633,DASHBOARD!$Q$7) -> 0.2 | AH633: =(100%+DASHBOARD!$Q$8)*'staging data'!T633 -> 1247.0485 | AI633: =(100%+DASHBOARD!$Q$9)*'staging data'!Y633 -> 37.2
V1048574: =MAX(V2:V1048573) -> 3661.07

Sheet ABC Analysis.SKU.Revenuecat.
E2: =0.8*88 -> 70.4
A3: Row Labels | B3: Sum of Gross Revenue(KES) | E3: =0.15*188 -> 28.2
A4: Accessories | B4: 1331648.9 | E4: =0.05*88 -> 4.4
A5: ACC-6626 | B5: 79082.507
A6: ACC-2988 | B6: 53034.364
A7: ACC-9283 | B7: 46450.26
A8: ACC-9533 | B8: 43084.872
A9: ACC-8098 | B9: 38096.184
A10: ACC-4490 | B10: 35396.278
A11: ACC-7838 | B11: 35167.745
A12: ACC-5177 | B12: 34139.16
A13: ACC-9162 | B13: 33062.236
A14: ACC-7078 | B14: 32086.376
A15: ACC-1375 | B15: 31513.085
A16: ACC-1659 | B16: 28386.016
... A641: Grand Total | B641: 10928846

Sheet SKU Top10byrevenue
A3: Row Labels | B3: Sum of Gross Revenue(KES)
A4: CMP-8851 | B4: 139277.83
A5: NET-2365 | B5: 109244
A6: LAP-8910 | B6: 102122.94
A7: MON-6962 | B7: 92715.25
A8: MON-2266 | B8: 87404.93
A9: MON-6699 | B9: 85637.74
A10: CMP-3938 | B10: 84136.12
A11: LAP-3904 | B11: 82514.712
A12: NET-5987 | B12: 82141.34
A13: NET-5523 | B13: 79548.756
A14: ACC-6626 | B14: 79082.507
A15: MON-5188 | B15: 72665.817
... A634: Grand Total | B634: 10928846

Sheet Top10SKU.chart
A3: Row Labels | B3: Sum of Sum of Gross Revenue(KES)
A4: CMP-3938 | B4: 84136.12
A5: CMP-8851 | B5: 139277.83
A6: LAP-3904 | B6: 82514.712
A7: LAP-8910 | B7: 102122.94
A8: MON-2266 | B8: 87404.93
A9: MON-6699 | B9: 85637.74
A10: MON-6962 | B10: 92715.25
A11: NET-2365 | B11: 109244
A12: NET-5523 | B12: 79548.756
A13: NET-5987 | B13: 82141.34
A14: Grand Total | B14: 944743.62

Sheet Pivot.Top10SKU
A2: Row Labels | B2: Sum of Gross Revenue(KES)
A3: CMP-8851 | B3: 139277.83
A4: NET-2365 | B4: 109244
A5: LAP-8910 | B5: 102122.94
A6: MON-6962 | B6: 92715.25
A7: MON-2266 | B7: 87404.93
A8: MON-6699 | B8: 85637.74
A9: CMP-3938 | B9: 84136.12
A10: LAP-3904 | B10: 82514.712
A11: NET-5987 | B11: 82141.34
A12: NET-5523 | B12: 79548.756

Sheet Revenueperchannel
A3: Row Labels | B3: Sum of Gross Revenue(KES) | C3: Sum of Gross Profit(KES)
A4: Direct | B4: 2700246.9 | C4: 958937.55
A5: Distributor | B5: 2038525.3 | C5: 632067.34
A6: Marketplace | B6: 2046341.5 | C6: 521734.32
A7: Online | B7: 2131682.2 | C7: 757285.3
A8: Retail | B8: 2012049.9 | C8: 531073.5
A9: Grand Total | B9: 10928846 | C9: 3401098

Sheet Documentation
A1: EXPLANATION / DOCUMENTING ASSIGNMENT FORMULAS AND METHODS I USED
A2: Juliet Kiplimo - Data Science. Assignment Week 2.
A3: Part A — Data Cleaning & Preparation:
A4: 1) Create a staging table where you:
A5: • Remove exact duplicate rows: >> Selected Employee ID Column >> go to data cleanup >> Select that your data has headers and remove duplicates
A6: • Fix data types (dates as Dates, numeric fields as numbers).>. Format cells tool
A7: • Handle missing values for City, Salesperson, and Channel using reasonable business logic >> Use CTRL + G>> Blanks and the Filter function, Check for similarities and patterns.
A8: • Flag and correct suspicious UnitPrice values (e.g., negative prices) and discounts (e.g., > 30%). >> Use conditional formatting to Highlight all values less than 0, then create a new column and use ABS() formula to correct negative prices. Then hide the column with negative prices.
A9: • Ensure RequiredDate is not earlier than OrderDate; where it is, impute a corrected RequiredDate (explain your rule). >> Use the IF() function : if required date>= to Order_date, return same date, else required_date- leadtime) I use subtraction because leadtime is a negative integer
A10: • Add a derived 'LeadTimeDays' = RequiredDate − OrderDate (in days). >> Use the DAYS() function to extract the number of days Until the order is required.
A14: 2) Create calculated columns (do these in Excel, not by formula in the data source):
A15: • GrossRevenue = UnitPrice × Quantity × (1 − DiscountPct).
... A40: • Share of orders with DiscountPct > 20% by Region and Salesperson; list outliers.

Sheet Leadtimedays(%)
A3: Row Labels | B3: Count of %leadtime >7days | C3: Count of OrderID
A4: Achieved | B4: 0.71428571 | C4: 65
A5: Africa | B5: 0.15384615 | C5: 14
A6: Americas | B6: 0.13186813 | C6: 12
A7: Asia | B7: 0.25274725 | C7: 23
A8: Europe | B8: 0.17582418 | C8: 16
A9: Not achieved | B9: 0.28571429 | C9: 26
A10: Africa | B10: 0.087912088 | C10: 8
A11: Americas | B11: 0.065934066 | C11: 6
A12: Asia | B12: 0.054945055 | C12: 5
A13: Europe | B13: 0.076923077 | C13: 7
A14: Grand Total | B14: 1 | C14: 91

Sheet Profitper.Region.Channel
A3: Sum of Gross Profit(KES) | B3: Column Labels
A4: Row Labels | B4: Direct | C4: Distributor | D4: Marketplace | E4: Online | F4: Retail | G4: Grand Total
A5: Brazil | B5: 126313.68 | C5: 86999.592 | D5: 31381.503 | E5: 66999.956 | F5: 39137.677 | G5: 350832.41
A6: Canada | B6: 87068.557 | C6: 46415.507 | D6: 31800.796 | E6: 116963.9 | F6: 7570.6977 | G6: 289819.46
A7: China | B7: 93092.11 | C7: 28395.209 | D7: 58581.624 | E7: 81927.941 | F7: 26927.824 | G7: 288924.71
A8: France | B8: 84038.081 | C8: 16707.597 | D8: -15977.402 | E8: 34792.922 | F8: 53376.509 | G8: 172937.71
A9: Germany | B9: 144284.62 | C9: 42975.152 | D9: 51326.275 | E9: 68202.412 | F9: 24326.57 | G9: 331115.03
A10: India | B10: 82325.917 | C10: 53215.883 | D10: 51462.982 | E10: 13005.427 | F10: 87519.608 | G10: 287529.82
A11: Japan | B11: 53799.451 | C11: 69535.654 | D11: 38547.948 | E11: 54109.021 | F11: 38811.128 | G11: 254803.2
A12: Kenya | B12: 113946.29 | C12: 58662.09 | D12: 2699.974 | E12: 50056.937 | F12: 50530.408 | G12: 275895.7
A13: Nigeria | B13: 22534.408 | C13: 39872.954 | D13: 66637.259 | E13: 85419.948 | F13: 67499.278 | G13: 281963.85
A14: South Africa | B14: 41847.49 | C14: 93507.309 | D14: 95502.072 | E14: 9977.0607 | F14: 38970.37 | G14: 279804.3
A15: United Kingdom | B15: 64394.252 | C15: 53896.809 | D15: 76343.937 | E15: 97071.829 | F15: 74076.094 | G15: 365782.92
A16: USA | B16: 45292.691 | C16: 41883.586 | D16: 33427.348 | E16: 78757.948 | F16: 22327.335 | G16: 221688.91
A17: Grand Total | B17: 958937.55 | C17: 632067.34 | D17: 521734.32 | E17: 757285.3 | F17: 531073.5 | G17: 3401098

Sheet Discount outliers
B1: Discount.Pct
B2: 0.226
B3: 0.207
B4: 0.211
B5: 0.212
B6: 0.237
B7: 0.208
B8: 0.212
B9: 0.248
B10: 0.225
B11: 0.209
B12: 0.235
B13: 0.218
... B91: 0.237

Sheet First.month sales per country
A3: Row Labels | B3: Sum of Gross Revenue
A4: q1 | B4: 317426.51
A5: Brazil | B5: 40903.902
A6: 2025 | B6: 40903.902
A7: Canada | B7: 8128.5187
A8: China | B8: 1446.9507
A9: 2024 | B9: 1446.9507
A10: France | B10: 19244.448
A11: 2024 | B11: 7203.8047
A12: 2025 | B12: 12040.644
A13: Germany | B13: 96020.399
A14: 2023 | B14: 85637.74
A15: 2025 | B15: 10382.659
... A31: Grand Total | B31: 963190.85

Sheet ABC Analysis
A3: Row Labels | B3: Sum of Gross Revenue
A4: Accessories | B4: 1331648.9
A5: ACC-6626 | B5: 79082.507
A6: ACC-2988 | B6: 53034.364
A7: ACC-9283 | B7: 46450.26
A8: ACC-9533 | B8: 43084.872
A9: ACC-8098 | B9: 38096.184
A10: ACC-4490 | B10: 35396.278
A11: ACC-7838 | B11: 35167.745
A12: ACC-5177 | B12: 34139.16
A13: ACC-9162 | B13: 33062.236
A14: ACC-7078 | B14: 32086.376
A15: ACC-1375 | B15: 31513.085
... A98: Printers | B98: 1616102.7
A99: (blank)
A100: (blank)
A101: Grand Total | B101: 10928846

Sheet Sales productivityperson
A3: Row Labels | B3: Sum of Gross Profit
A4: A. Patel | B4: 278058.39
A5: B. Chen | B5: 315969.97
A6: C. Otieno | B6: 228052.28
A7: D. Smith | B7: 152346.9
A8: E. Garcia | B8: 204981.34
A9: F. Müller | B9: 298697.35
A10: G. Dubois | B10: 172441.87
A11: H. Kim | B11: 137020.81
A12: H.Kim | B12: 21088.284
A13: I. Johnson | B13: 140021.69
A14: J. Njeri | B14: 281839.01
A15: K. Singh | B15: 278762.27
... A19: O. Wang | B19: 185219.44
A20: (blank)
A21: Grand Total | B21: 3401098

Sheet Revenuepermonth.
A3: Row Labels | B3: Sum of Gross Revenue
A4: Jan | B4: 67681.434
A5: Feb | B5: 89950.744
A6: Mar | B6: 68565.902
A7: Apr | B7: 37576.076
A8: May | B8: 58782.593
A9: Jun | B9: 131498.48
A10: Jul | B10: 71477.459
A11: Aug | B11: 97781.086
A12: Sept | B12: 35378.651
A13: Oct | B13: 131228.32
A14: Nov | B14: 4071.8
A15: Dec | B15: 100797.83
A16: Grand Total | B16: 894790.38

Sheet OrderCount.Quarterly
A3: Count of OrderID | B3: Column Labels
A4: Year | B4: Qtr1 | C4: Qtr2 | D4: Qtr3 | E4: Qtr4 | F4: Grand Total
A5: 2023 | B5: 47 | C5: 71 | D5: 59 | E5: 49 | F5: 226
A6: 2024 | B6: 64 | C6: 60 | D6: 52 | E6: 62 | F6: 238
A7: 2025 | B7: 52 | C7: 67 | D7: 49 | F7: 168
A8: Grand Total | B8: 163 | C8: 198 | D8: 160 | E8: 111 | F8: 632

Sheet Regional.Hierachy
A1: Region | B1: (All)
A3: Row Labels | B3: Count of OrderID | C3: Count of OrderID2
A4: Brazil | B4: 62 | C4: 62
A5: Canada | B5: 44 | C5: 44
A6: China | B6: 51 | C6: 51
A7: France | B7: 54 | C7: 54
A8: Germany | B8: 51 | C8: 51
A9: India | B9: 61 | C9: 61
A10: Japan | B10: 59 | C10: 59
A11: Kenya | B11: 56 | C11: 56
A12: Nigeria | B12: 44 | C12: 44
A13: South Africa | B13: 45 | C13: 45
A14: United Kingdom | B14: 54 | C14: 54
A15: USA | B15: 51 | C15: 51
A16: Grand Total | B16: 632 | C16: 632
